{"name":"HAT-P-35","stars":[{"name":"HAT-P-35","type":"star","spec":"F","temp":6096,"radius":1.44,"lum":2.55137,"minhz":1.183,"maxhz":2.747,"texture":""}],"satellites":[{"name":"HAT-P-35 b","type":"planet","masse":335.11,"distance":535,"temp":1442,"radius":14.92,"semiMajorAxis":7449973.96086,"eccentricity":"0.03","inclination":"87.3","siderealOrbitPeriod":3.65,"omega":248,"habitable":"0","esi":"0.0","habitableMoon":"0","method":"transit","year":"2012","tempClass":"hot","class":"jovian","color":null,"texture":"hot-jovian.jpg"}]}