{"name":"HD 118203","stars":[{"name":"HD 118203","type":"star","spec":"K","temp":5600,"radius":2.31,"lum":4.686703,"minhz":1.636,"maxhz":3.882,"texture":""}],"satellites":[{"name":"HD 118203 b","type":"planet","masse":677.21,"distance":88.6,"temp":1408,"radius":11.32,"semiMajorAxis":10471850.949,"eccentricity":"0.31","inclination":"0.0","siderealOrbitPeriod":6.13,"omega":155.7,"habitable":"0","esi":"0.1","habitableMoon":"0","method":"radial velocity","year":"2005","tempClass":"hot","class":"jovian","color":null,"texture":"hot-jovian.jpg"}]}