{"name":"HD 17156","stars":[{"name":"HD 17156","type":"star","spec":"G","temp":6079,"radius":1.51,"lum":2.786256,"minhz":1.238,"maxhz":2.875,"texture":""}],"satellites":[{"name":"HD 17156 b","type":"planet","masse":1014.55,"distance":78.24,"temp":790.5,"radius":12.26,"semiMajorAxis":24279734.41461,"eccentricity":"0.68","inclination":"87.2","siderealOrbitPeriod":21.22,"omega":121.7,"habitable":"0","esi":"0.0","habitableMoon":"0","method":"transit","year":"2007","tempClass":"hot","class":"jovian","color":null,"texture":"hot-jovian.jpg"}]}