{"name":"HD 204313","stars":[{"name":"HD 204313","type":"star","spec":"G","temp":5767,"radius":1.12,"lum":1.244534,"minhz":0.837,"maxhz":1.972,"texture":""}],"satellites":[{"name":"HD 204313 b","type":"planet","masse":1128.69,"distance":47.37,"temp":153.8,"radius":11.63,"semiMajorAxis":454777526.928,"eccentricity":"0.23","inclination":"0.0","siderealOrbitPeriod":1920.1,"omega":298,"habitable":"0","esi":"0.2","habitableMoon":"0","method":"radial velocity","year":"2009","tempClass":"cold","class":"jovian","color":null,"texture":"cold-jovian.jpg"},{"name":"HD 204313 c","type":"planet","masse":17.17,"distance":47.37,"temp":585.7,"radius":4.42,"semiMajorAxis":31460432.20821,"eccentricity":"0.17","inclination":"0.0","siderealOrbitPeriod":34.87,"omega":0,"habitable":"0","esi":"0.2","habitableMoon":"0","method":"radial velocity","year":"2011","tempClass":"hot","class":"neptunian","color":null,"texture":"hot-neptunian.jpg"},{"name":"HD 204313 d","type":"planet","masse":534.14,"distance":47.37,"temp":135.1,"radius":11.06,"semiMajorAxis":587919631.851,"eccentricity":"0.28","inclination":"0.0","siderealOrbitPeriod":2831.6,"omega":247,"habitable":"0","esi":"0.1","habitableMoon":"0","method":"radial velocity","year":"2012","tempClass":"cold","class":"jovian","color":null,"texture":"cold-jovian.jpg"}]}