{"name":"HD 20868","stars":[{"name":"HD 20868","type":"star","spec":"K","temp":4795,"radius":0.79,"lum":0.296005,"minhz":0.424,"maxhz":1.047,"texture":""}],"satellites":[{"name":"HD 20868 b","type":"planet","masse":632.7,"distance":48.9,"temp":185.1,"radius":11.25,"semiMajorAxis":141669183.5529,"eccentricity":"0.75","inclination":"0.0","siderealOrbitPeriod":380.85,"omega":356.2,"habitable":"0","esi":"0.3","habitableMoon":"0","method":"radial velocity","year":"2008","tempClass":"warm","class":"jovian","color":null,"texture":"warm-jovian.jpg"}]}