{"name":"HD 93083","stars":[{"name":"HD 93083","type":"star","spec":"K","temp":4995,"radius":0.85,"lum":0.396092,"minhz":0.487,"maxhz":1.19,"texture":""}],"satellites":[{"name":"HD 93083 b","type":"planet","masse":117.64,"distance":28.9,"temp":292.3,"radius":8.16,"semiMajorAxis":71358184.3239,"eccentricity":"0.14","inclination":"0.0","siderealOrbitPeriod":143.58,"omega":333.5,"habitable":"0","esi":"0.4","habitableMoon":"0","method":"radial velocity","year":"2005","tempClass":"hot","class":"jovian","color":null,"texture":"hot-jovian.jpg"}]}