{"name":"Kepler-125","stars":[{"name":"Kepler-125","type":"star","spec":"K","temp":3810,"radius":0.51,"lum":0.049173,"minhz":0.178,"maxhz":0.462,"texture":""}],"satellites":[{"name":"Kepler-125 b","type":"planet","masse":20.8,"distance":0,"temp":592.5,"radius":2.36,"semiMajorAxis":6133512.6987,"eccentricity":"0.00","inclination":"0.0","siderealOrbitPeriod":4.16,"omega":0,"habitable":"0","esi":"0.2","habitableMoon":"0","method":"transit","year":"2014","tempClass":"hot","class":"superterran","color":null,"texture":"hot-superterran.jpg"},{"name":"Kepler-125 c","type":"planet","masse":0.32,"distance":0,"temp":531.2,"radius":0.74,"semiMajorAxis":7629491.4057,"eccentricity":"0.00","inclination":"0.0","siderealOrbitPeriod":5.77,"omega":0,"habitable":"0","esi":"0.3","habitableMoon":"0","method":"transit","year":"2014","tempClass":"hot","class":"subterran","color":null,"texture":"hot-subterran.jpg"}]}