{"name":"Kepler-122","stars":[{"name":"Kepler-122","type":"star","spec":"F","temp":6050,"radius":1.22,"lum":1.789085,"minhz":0.993,"maxhz":2.309,"texture":""}],"satellites":[{"name":"Kepler-122 b","type":"planet","masse":19.94,"distance":0,"temp":1164,"radius":2.34,"semiMajorAxis":9574263.7248,"eccentricity":"0.00","inclination":"0.0","siderealOrbitPeriod":5.77,"omega":0,"habitable":"0","esi":"0.2","habitableMoon":"0","method":"transit","year":"2014","tempClass":"hot","class":"superterran","color":null,"texture":"hot-superterran.jpg"},{"name":"Kepler-122 c","type":"planet","masse":40.25,"distance":0,"temp":896.6,"radius":5.87,"semiMajorAxis":16156570.0356,"eccentricity":"0.00","inclination":"0.0","siderealOrbitPeriod":12.47,"omega":0,"habitable":"0","esi":"0.1","habitableMoon":"0","method":"transit","year":"2014","tempClass":"hot","class":"neptunian","color":null,"texture":"hot-neptunian.jpg"},{"name":"Kepler-122 d","type":"planet","masse":15.1,"distance":0,"temp":748.4,"radius":2.2,"semiMajorAxis":23187669.9585,"eccentricity":"0.00","inclination":"0.0","siderealOrbitPeriod":21.59,"omega":0,"habitable":"0","esi":"0.2","habitableMoon":"0","method":"transit","year":"2014","tempClass":"hot","class":"superterran","color":null,"texture":"hot-superterran.jpg"},{"name":"Kepler-122 e","type":"planet","masse":3.33,"distance":0,"temp":618.4,"radius":2.6,"semiMajorAxis":33958716.6489,"eccentricity":"0.00","inclination":"0.0","siderealOrbitPeriod":37.99,"omega":0,"habitable":"0","esi":"0.2","habitableMoon":"0","method":"transit","year":"2014","tempClass":"hot","class":"neptunian","color":null,"texture":"hot-neptunian.jpg"}]}