{"name":"Kepler-182","stars":[{"name":"Kepler-182","type":"star","spec":"F","temp":6250,"radius":1.15,"lum":1.810529,"minhz":0.991,"maxhz":2.286,"texture":""}],"satellites":[{"name":"Kepler-182 b","type":"planet","masse":3.24,"distance":0,"temp":953.8,"radius":2.58,"semiMajorAxis":14361395.5872,"eccentricity":"0.00","inclination":"0.0","siderealOrbitPeriod":9.83,"omega":0,"habitable":"0","esi":"0.2","habitableMoon":"0","method":"transit","year":"2014","tempClass":"hot","class":"neptunian","color":null,"texture":"hot-neptunian.jpg"},{"name":"Kepler-182 c","type":"planet","masse":7.97,"distance":0,"temp":745.8,"radius":3.43,"semiMajorAxis":23486865.6999,"eccentricity":"0.00","inclination":"0.0","siderealOrbitPeriod":20.68,"omega":0,"habitable":"0","esi":"0.2","habitableMoon":"0","method":"transit","year":"2014","tempClass":"hot","class":"neptunian","color":null,"texture":"hot-neptunian.jpg"}]}