{"name":"KIC-8552719","stars":[{"name":"KIC-8552719","type":"star","spec":"K","temp":5114,"radius":0.82,"lum":0.414645,"minhz":0.496,"maxhz":1.205,"texture":""}],"satellites":[{"name":"KIC-8552719 b","type":"planet","masse":8.7,"distance":0,"temp":459.9,"radius":3.53,"semiMajorAxis":29560539.25032,"eccentricity":"0.00","inclination":"89.5","siderealOrbitPeriod":88.41,"omega":0,"habitable":"0","esi":"0.2","habitableMoon":"0","method":"transit","year":"2012","tempClass":"hot","class":"neptunian","color":null,"texture":"hot-neptunian.jpg"}]}