{"name":"WASP-25","stars":[{"name":"WASP-25","type":"star","spec":"G","temp":5750,"radius":0.95,"lum":0.885133,"minhz":0.707,"maxhz":1.666,"texture":""}],"satellites":[{"name":"WASP-25 b","type":"planet","masse":184.41,"distance":169,"temp":1135,"radius":14.11,"semiMajorAxis":7090939.07118,"eccentricity":"0.00","inclination":"87.7","siderealOrbitPeriod":3.76,"omega":0,"habitable":"0","esi":"0.0","habitableMoon":"0","method":"transit","year":"2010","tempClass":"hot","class":"jovian","color":null,"texture":"hot-jovian.jpg"}]}