{"name":"WASP-17","stars":[{"name":"WASP-17","type":"star","spec":"F","temp":6650,"radius":1.38,"lum":3.341447,"minhz":1.327,"maxhz":3.015,"texture":""}],"satellites":[{"name":"WASP-17 b","type":"planet","masse":154.52,"distance":0,"temp":1517,"radius":22.3,"semiMajorAxis":7704290.34105,"eccentricity":"0.03","inclination":"86.8","siderealOrbitPeriod":3.74,"omega":277.4,"habitable":"0","esi":"0.0","habitableMoon":"0","method":"transit","year":"2009","tempClass":"hot","class":"jovian","color":null,"texture":"hot-jovian.jpg"}]}